snippet/__init__.py
snippet/__main__.py
snippet/_version.py
snippet/api.py
snippet/cli.py
snippet/config.py
snippet/exceptions.py
snippet/snippet.py
snippet/workflow.py
snippet/_internal/__init__.py
snippet/_internal/file_wrangler.py
snippet/_internal/logs.py
snippet/_internal/util.py
snippet/_internal/wrapper.py
code_snippet-2.0.1.dist-info/LICENSE
code_snippet-2.0.1.dist-info/METADATA
code_snippet-2.0.1.dist-info/WHEEL
code_snippet-2.0.1.dist-info/entry_points.txt
code_snippet-2.0.1.dist-info/top_level.txt
code_snippet-2.0.1.dist-info/RECORD
