Metadata-Version: 2.1
Name: code-snippet
Version: 2.0.1
Summary: Code snippet extraction for documentation
Home-page: https://github.com/ARMmbed/snippet
Author: David Hyman, Mbed team
Author-email: support@mbed.com
License: Apache 2.0
Keywords: documentation-generator documentation-tool snippet-generator snippet project-management documentation
Platform: UNKNOWN
Classifier: Development Status :: 3 - Alpha
Classifier: Intended Audience :: Developers
Classifier: License :: OSI Approved :: Apache Software License
Classifier: Programming Language :: Python
Classifier: Programming Language :: Python :: 3 :: Only
Classifier: Programming Language :: Python :: 3.6
Classifier: Programming Language :: Python :: 3.7
Classifier: Programming Language :: Python :: 3.8
Classifier: Topic :: Software Development :: Build Tools
Classifier: Topic :: Documentation
Classifier: Topic :: Software Development :: Documentation
Requires-Python: >=3.6,<4
Requires-Dist: python-dotenv
Requires-Dist: toml
Requires-Dist: pystache
Requires-Dist: mbed-tools-lib
